limacharlie/ARL.py
limacharlie/Billing.py
limacharlie/Configs.py
limacharlie/DRCli.py
limacharlie/Extensions.py
limacharlie/Firehose.py
limacharlie/Hive.py
limacharlie/Jobs.py
limacharlie/Logs.py
limacharlie/Manager.py
limacharlie/Model.py
limacharlie/Payloads.py
limacharlie/Query.py
limacharlie/Replay.py
limacharlie/Replicants.py
limacharlie/Search.py
limacharlie/SearchAPI.py
limacharlie/Sensor.py
limacharlie/SpotCheck.py
limacharlie/Spout.py
limacharlie/Sync.py
limacharlie/User.py
limacharlie/UserPreferences.py
limacharlie/Webhook.py
limacharlie/WebhookSender.py
limacharlie/__init__.py
limacharlie/__main__.py
limacharlie/constants.py
limacharlie/oauth.py
limacharlie/oauth_firebase_simple.py
limacharlie/oauth_mfa.py
limacharlie/oauth_server.py
limacharlie/oauth_simple.py
limacharlie/request_utils.py
limacharlie/term_utils.py
limacharlie/time_utils.py
limacharlie/user_agent_utils.py
limacharlie/utils.py
limacharlie/versions.py
limacharlie-4.11.3.dist-info/licenses/LICENSE
limacharlie-4.11.3.dist-info/METADATA
limacharlie-4.11.3.dist-info/WHEEL
limacharlie-4.11.3.dist-info/entry_points.txt
limacharlie-4.11.3.dist-info/top_level.txt
limacharlie-4.11.3.dist-info/zip-safe
limacharlie-4.11.3.dist-info/RECORD
