Metadata-Version: 2.4
Name: limacharlie
Version: 4.11.3
Summary: Python API for LimaCharlie.io
Home-page: https://limacharlie.io
Author: Maxime Lamothe-Brassard ( Refraction Point, Inc )
Author-email: maxime@refractionpoint.com
License: Apache v2
License-File: LICENSE
Requires-Dist: requests
Requires-Dist: passlib
Requires-Dist: pyyaml
Requires-Dist: tabulate
Requires-Dist: termcolor
Requires-Dist: pygments
Requires-Dist: rich
Requires-Dist: cryptography>=44.0.1
Dynamic: author
Dynamic: author-email
Dynamic: description
Dynamic: home-page
Dynamic: license
Dynamic: license-file
Dynamic: requires-dist
Dynamic: summary
